{"generatedAt":"2026-04-23T12:47:08.847Z","bucketSize":"1d","windowDays":365,"services":[{"service":"arolariu.ro","buckets":[{"t":"2026-04-21T00:00:00.000Z","status":"Healthy","probes":{"healthy":150,"total":150},"latency":{"p50":624,"p75":685,"p95":998,"p99":1824},"httpStatus":200},{"t":"2026-04-22T00:00:00.000Z","status":"Healthy","probes":{"healthy":150,"total":150},"latency":{"p50":583,"p75":684,"p95":967,"p99":1547},"httpStatus":200},{"t":"2026-04-23T00:00:00.000Z","status":"Healthy","probes":{"healthy":70,"total":70},"latency":{"p50":568,"p75":689,"p95":1002,"p99":2244},"httpStatus":200}]},{"service":"api.arolariu.ro","buckets":[{"t":"2026-04-21T00:00:00.000Z","status":"Healthy","probes":{"healthy":150,"total":150},"latency":{"p50":602,"p75":680,"p95":1021,"p99":1150},"httpStatus":200},{"t":"2026-04-22T00:00:00.000Z","status":"Healthy","probes":{"healthy":150,"total":150},"latency":{"p50":596,"p75":698,"p95":1107,"p99":2574},"httpStatus":200},{"t":"2026-04-23T00:00:00.000Z","status":"Healthy","probes":{"healthy":70,"total":70},"latency":{"p50":567,"p75":617,"p95":951,"p99":1370},"httpStatus":200}],"subSeries":{"mssql":[{"t":"2026-04-21T00:00:00.000Z","status":"Healthy","probes":{"healthy":150,"total":150},"latency":{"p50":2,"p75":3,"p95":188,"p99":258}},{"t":"2026-04-22T00:00:00.000Z","status":"Healthy","probes":{"healthy":150,"total":150},"latency":{"p50":2,"p75":2,"p95":125,"p99":337}},{"t":"2026-04-23T00:00:00.000Z","status":"Healthy","probes":{"healthy":70,"total":70},"latency":{"p50":2,"p75":2,"p95":155,"p99":240}}],"blob-storage":[{"t":"2026-04-21T00:00:00.000Z","status":"Healthy","probes":{"healthy":150,"total":150},"latency":{"p50":5,"p75":8,"p95":75,"p99":143}},{"t":"2026-04-22T00:00:00.000Z","status":"Healthy","probes":{"healthy":150,"total":150},"latency":{"p50":5,"p75":7,"p95":56,"p99":161}},{"t":"2026-04-23T00:00:00.000Z","status":"Healthy","probes":{"healthy":70,"total":70},"latency":{"p50":6,"p75":7,"p95":70,"p99":110}}],"exp":[{"t":"2026-04-21T00:00:00.000Z","status":"Healthy","probes":{"healthy":150,"total":150},"latency":{"p50":47,"p75":83,"p95":216,"p99":366}},{"t":"2026-04-22T00:00:00.000Z","status":"Healthy","probes":{"healthy":150,"total":150},"latency":{"p50":39,"p75":81,"p95":282,"p99":1562}},{"t":"2026-04-23T00:00:00.000Z","status":"Healthy","probes":{"healthy":70,"total":70},"latency":{"p50":43,"p75":88,"p95":266,"p99":701}}]}},{"service":"exp.arolariu.ro","buckets":[{"t":"2026-04-21T00:00:00.000Z","status":"Healthy","probes":{"healthy":150,"total":150},"latency":{"p50":581,"p75":670,"p95":894,"p99":1433},"httpStatus":200},{"t":"2026-04-22T00:00:00.000Z","status":"Healthy","probes":{"healthy":150,"total":150},"latency":{"p50":579,"p75":649,"p95":941,"p99":2018},"httpStatus":200},{"t":"2026-04-23T00:00:00.000Z","status":"Healthy","probes":{"healthy":70,"total":70},"latency":{"p50":575,"p75":622,"p95":909,"p99":1378},"httpStatus":200}]},{"service":"cv.arolariu.ro","buckets":[{"t":"2026-04-21T00:00:00.000Z","status":"Healthy","probes":{"healthy":150,"total":150},"latency":{"p50":611,"p75":841,"p95":1647,"p99":2064},"httpStatus":200},{"t":"2026-04-22T00:00:00.000Z","status":"Healthy","probes":{"healthy":150,"total":150},"latency":{"p50":596,"p75":777,"p95":1711,"p99":2063},"httpStatus":200},{"t":"2026-04-23T00:00:00.000Z","status":"Healthy","probes":{"healthy":70,"total":70},"latency":{"p50":558,"p75":799,"p95":1590,"p99":1906},"httpStatus":200}]}]}